findopendata/__init__.py
findopendata/celery.py
findopendata/ckan_crawler.py
findopendata/column_sketch.py
findopendata/download.py
findopendata/indexing.py
findopendata/metadata.py
findopendata/settings.py
findopendata/socrata_crawler.py
findopendata/table_sketch.py
findopendata/util.py
findopendata/ckan/__init__.py
findopendata/models/__init__.py
findopendata/models/language_models.py
findopendata/models/word_vector_models.py
findopendata/parsers/__init__.py
findopendata/parsers/avro.py
findopendata/parsers/csv.py
findopendata/parsers/encoding.py
findopendata/parsers/jsonl.py
findopendata/socrata/__init__.py
findopendata/storage/__init__.py
findopendata/storage/azure.py
findopendata/storage/base.py
findopendata/storage/factory.py
findopendata/storage/gcp.py
findopendata/storage/local.py
findopendata/storage/objects.py
findopendata-1.0.5.data/scripts/generate_metadata.py
findopendata-1.0.5.data/scripts/harvest_datasets.py
findopendata-1.0.5.data/scripts/sketch_dataset_content.py
findopendata-1.0.5.dist-info/LICENSE
findopendata-1.0.5.dist-info/METADATA
findopendata-1.0.5.dist-info/WHEEL
findopendata-1.0.5.dist-info/top_level.txt
findopendata-1.0.5.dist-info/RECORD
