Metadata-Version: 2.1
Name: findopendata
Version: 1.0.5
Summary: A search engine for Open Data.
Home-page: https://github.com/findopendata/findopendata
Author: Eric Zhu
Author-email: 
Keywords: open-data search-engine
Classifier: Programming Language :: Python :: 3
Classifier: License :: OSI Approved :: Apache Software License
Classifier: Operating System :: OS Independent
Requires-Python: >=3.6
License-File: LICENSE
Requires-Dist: requests (>=2.22.0)
Requires-Dist: google-cloud-storage (>=1.17.0)
Requires-Dist: azure-storage-blob (>=12.14.1)
Requires-Dist: google-auth (>=1.6.3)
Requires-Dist: gcsfs (>=0.3.0)
Requires-Dist: celery (>=4.3.0)
Requires-Dist: psycopg2-binary (>=2.7.5)
Requires-Dist: Django (>=2.2.3)
Requires-Dist: rfc6266-content-disposition (>=0.0.6)
Requires-Dist: simplejson (>=3.16.0)
Requires-Dist: genson (>=1.1.0)
Requires-Dist: fastavro (>=0.22.3)
Requires-Dist: python-snappy (>=0.5.4)
Requires-Dist: python-dateutil (>=2.8.0)
Requires-Dist: datasketch (>=1.4.10)
Requires-Dist: pyfarmhash (>=0.2.2)
Requires-Dist: cchardet (>=2.1.4)
Requires-Dist: spacy (>=2.1.8)
Requires-Dist: beautifulsoup4 (>=4.8.0)
Requires-Dist: pyyaml (>=5.1.2)
Requires-Dist: gevent (>=1.4.0)
Provides-Extra: test
Requires-Dist: nose2 (>=0.9.1) ; extra == 'test'
